<?xml version="1.0" encoding="utf-8"?>
<!--
     Copyright 2019 Coop IT Easy
     License AGPL-3.0 or later (http://www.gnu.org/licenses/agpl).
-->
<odoo>
    <record id="beesdoo_base.res_partner_cooperator_1_demo" model="res.partner">
        <field name="cooperator_type">share_a</field>
    </record>

    <record id="beesdoo_base.res_partner_cooperator_2_demo" model="res.partner">
        <field name="cooperator_type">share_a</field>
    </record>

    <record id="beesdoo_base.res_partner_cooperator_3_demo" model="res.partner">
        <field name="cooperator_type">share_a</field>
    </record>

    <record id="beesdoo_base.res_partner_cooperator_4_demo" model="res.partner">
        <field name="cooperator_type">share_a</field>
    </record>

    <record id="beesdoo_base.res_partner_cooperator_5_demo" model="res.partner">
        <field name="cooperator_type">share_a</field>
    </record>

    <record id="beesdoo_base.res_partner_cooperator_6_demo" model="res.partner">
        <field name="cooperator_type">share_a</field>
    </record>
</odoo>
